math_jaime/primos.py
math_jaime-0.1.dist-info/LICENSE
math_jaime-0.1.dist-info/METADATA
math_jaime-0.1.dist-info/WHEEL
math_jaime-0.1.dist-info/top_level.txt
math_jaime-0.1.dist-info/RECORD
