Metadata-Version: 2.1
Name: math-jaime
Version: 0.1
Summary: Utilidades matematicas
Home-page: UNKNOWN
Author: Jaime Casado
Author-email: jaime.casado.a@gmail.com
License: GNU GPLv3
Keywords: math_jaime mathematical operations prime
Platform: UNKNOWN
Classifier: Intended Audience :: Developers
Classifier: Topic :: Utilities
Classifier: Programming Language :: Python :: 3
